hygrep/VERSION
hygrep/__init__.py
hygrep/_common.py
hygrep/cli.py
hygrep/embedder.py
hygrep/extractor.py
hygrep/mlx_embedder.py
hygrep/scanner.py
hygrep/semantic.py
hygrep/_scanner.so
hhg-0.0.32.dist-info/METADATA
hhg-0.0.32.dist-info/WHEEL
hhg-0.0.32.dist-info/entry_points.txt
hhg-0.0.32.dist-info/licenses/LICENSE
hhg-0.0.32.dist-info/RECORD
