Metadata-Version: 2.4
Name: hhg
Version: 0.0.32
Summary: Hybrid file search — semantic + keyword matching
Project-URL: Homepage, https://github.com/nijaru/hygrep
Project-URL: Repository, https://github.com/nijaru/hygrep
Author: nijaru
License-Expression: MIT
License-File: LICENSE
Keywords: cli,code,grep,search,semantic
Classifier: Development Status :: 3 - Alpha
Classifier: Environment :: Console
Classifier: Intended Audience :: Developers
Classifier: License :: OSI Approved :: MIT License
Classifier: Operating System :: MacOS
Classifier: Operating System :: POSIX :: Linux
Classifier: Programming Language :: Python :: 3
Classifier: Programming Language :: Python :: 3.11
Classifier: Programming Language :: Python :: 3.12
Classifier: Programming Language :: Python :: 3.13
Classifier: Topic :: Software Development :: Libraries :: Python Modules
Classifier: Topic :: Text Processing :: Filters
Requires-Python: <3.14,>=3.11
Requires-Dist: huggingface-hub>=0.20
Requires-Dist: numpy>=1.24
Requires-Dist: omendb>=0.0.23
Requires-Dist: onnxruntime>=1.16
Requires-Dist: pathspec>=0.11
Requires-Dist: rich>=13.0
Requires-Dist: tokenizers>=0.15
Requires-Dist: tree-sitter-bash>=0.23
Requires-Dist: tree-sitter-c-sharp>=0.23
Requires-Dist: tree-sitter-c>=0.23
Requires-Dist: tree-sitter-cpp>=0.23
Requires-Dist: tree-sitter-css>=0.25
Requires-Dist: tree-sitter-elixir>=0.3
Requires-Dist: tree-sitter-go>=0.23
Requires-Dist: tree-sitter-hcl>=1.2
Requires-Dist: tree-sitter-html>=0.23
Requires-Dist: tree-sitter-java>=0.23
Requires-Dist: tree-sitter-javascript>=0.23
Requires-Dist: tree-sitter-json>=0.24
Requires-Dist: tree-sitter-julia>=0.23
Requires-Dist: tree-sitter-kotlin>=1.0
Requires-Dist: tree-sitter-lua>=0.2
Requires-Dist: tree-sitter-php>=0.23
Requires-Dist: tree-sitter-python>=0.23
Requires-Dist: tree-sitter-ruby>=0.23
Requires-Dist: tree-sitter-rust>=0.23
Requires-Dist: tree-sitter-sql>=0.3
Requires-Dist: tree-sitter-svelte>=1.0
Requires-Dist: tree-sitter-swift>=0.0.1
Requires-Dist: tree-sitter-toml>=0.7
Requires-Dist: tree-sitter-typescript>=0.23
Requires-Dist: tree-sitter-yaml>=0.7
Requires-Dist: tree-sitter-zig>=1.0
Requires-Dist: tree-sitter>=0.24
Requires-Dist: typer>=0.9
Provides-Extra: cuda
Requires-Dist: onnxruntime-gpu>=1.19; (sys_platform == 'linux') and extra == 'cuda'
Provides-Extra: dev
Requires-Dist: pytest>=7.0; extra == 'dev'
Requires-Dist: ruff>=0.1; extra == 'dev'
Provides-Extra: mlx
Requires-Dist: mlx-embeddings>=0.0.5; (sys_platform == 'darwin') and extra == 'mlx'
Requires-Dist: mlx>=0.21; (sys_platform == 'darwin') and extra == 'mlx'
